talkwave/__init__.py
talkwave/__main__.py
talkwave/__version__.py
talkwave/core.py
talkwave/curl.py
talkwave/dir.py
talkwave/frontend.py
talkwave/parse.py
talkwave-0.0.6.dist-info/LICENSE-APACHE
talkwave-0.0.6.dist-info/LICENSE-MIT
talkwave-0.0.6.dist-info/METADATA
talkwave-0.0.6.dist-info/WHEEL
talkwave-0.0.6.dist-info/top_level.txt
talkwave-0.0.6.dist-info/RECORD
