Metadata-Version: 2.1
Name: talkwave
Version: 0.0.6
Summary: TalkWave is an AI chatbot for developers written in Python.
Home-page: https://github.com/sebastienrousseau/talkwave
Author: Sebastien Rousseau
Author-email: sebastian.rousseau@gmail.com
License: Apache License 2.0
Keywords: talkwave,chatbot,AI,machine learningnatural language processing OpenAI GPT-3 GPT3 GPT python
Classifier: Development Status :: 4 - Beta
Classifier: Intended Audience :: Developers
Classifier: Intended Audience :: Financial and Insurance Industry
Classifier: Topic :: Software Development :: Libraries :: Python Modules
Classifier: License :: OSI Approved :: Apache Software License
Classifier: Programming Language :: Python
Classifier: Programming Language :: Python :: 3
Classifier: Programming Language :: Python :: 3.9
Classifier: Programming Language :: Python :: 3.10
Classifier: Programming Language :: Python :: 3.11
Classifier: Operating System :: OS Independent
Requires-Python: >=3.9
License-File: LICENSE-APACHE
License-File: LICENSE-MIT
Requires-Dist: Flask (==2.2.3)
Requires-Dist: openai (==0.27.2)
Requires-Dist: python-dotenv (==1.0.0)
Requires-Dist: requests (==2.28.2)
Requires-Dist: tabulate (==0.9.0)
